cdot/__init__.py
cdot/data_release.py
cdot/hgvs/__init__.py
cdot/hgvs/dataproviders/__init__.py
cdot/hgvs/dataproviders/fasta_seqfetcher.py
cdot/hgvs/dataproviders/json_data_provider.py
cdot/pyhgvs/__init__.py
cdot/pyhgvs/pyhgvs_transcript.py
cdot-0.2.26.dist-info/LICENSE
cdot-0.2.26.dist-info/METADATA
cdot-0.2.26.dist-info/WHEEL
cdot-0.2.26.dist-info/top_level.txt
cdot-0.2.26.dist-info/RECORD
