Metadata-Version: 2.1
Name: cdot
Version: 0.2.26
Summary: Transcripts for HGVS libraries
Home-page: https://github.com/SACGF/cdot
Author: Dave Lawrence
Author-email: davmlaw@gmail.com
Project-URL: Bug Tracker, https://github.com/SACGF/cdot/issues
Classifier: Programming Language :: Python :: 3
Classifier: License :: OSI Approved :: MIT License
Classifier: Operating System :: OS Independent
Requires-Python: >=3.8
License-File: LICENSE
Requires-Dist: requests
Requires-Dist: intervaltree
Requires-Dist: bioutils>=0.5.8
Requires-Dist: lazy
